{
  "iteration_count": 39,
  "consecutive_failures": 1,
  "last_iteration": "0039-20260228-143949",
  "completed_items": [
    "New files: 13",
    "New files: 6",
    "New files: 6",
    "New files: 1",
    "New files: 3",
    "New files: 2",
    "New files: 5",
    "New files: 3",
    "New files: 1",
    "New files: 5",
    "New files: 6",
    "New files: 7",
    "New files: 1",
    "New files: 6",
    "New files: 1",
    "New files: 6",
    "New files: 12",
    "New files: 2",
    "New files: 6",
    "New files: 5",
    "New files: 3",
    "New files: 3",
    "New files: 3",
    "New files: 9",
    "New files: 2",
    "New files: 2"
  ],
  "module_versions": {},
  "status": "alive",
  "total_cost_usd": 69.42483184999999,
  "total_tokens": 76438665,
  "total_elapsed_seconds": 20844.214313030243,
  "current_milestone": "v1.0.0"
}